test/test.py
test/test_Personne.py
Personne-1.0.0.dist-info/LICENCE
Personne-1.0.0.dist-info/METADATA
Personne-1.0.0.dist-info/WHEEL
Personne-1.0.0.dist-info/entry_points.txt
Personne-1.0.0.dist-info/top_level.txt
Personne-1.0.0.dist-info/RECORD
