Metadata-Version: 2.1
Name: Personne
Version: 1.0.0
Summary: Tester les Personnes
Home-page: UNKNOWN
Author: Nassim
Author-email: nacimessi10@outlook.fr
License: MIT
Platform: UNKNOWN
Classifier: License :: OSI Approved :: MIT License
Classifier: Programming Language :: Python :: 3
Classifier: Programming Language :: Python :: 3.7
